pycoast/__init__.py
pycoast/conftest.py
pycoast/cw_agg.py
pycoast/cw_base.py
pycoast/cw_pil.py
pycoast/version.py
pycoast/tests/__init__.py
pycoast/tests/brazil_shapefiles.png
pycoast/tests/brazil_shapefiles_agg.png
pycoast/tests/coasts_and_grid.ini
pycoast/tests/coasts_and_grid_agg.ini
pycoast/tests/contours_europe.png
pycoast/tests/contours_europe_agg.png
pycoast/tests/contours_europe_alpha.png
pycoast/tests/contours_geos.png
pycoast/tests/contours_geos_agg.png
pycoast/tests/dateline_boundary_cross.png
pycoast/tests/dateline_cross.png
pycoast/tests/eastern_shapes_agg.png
pycoast/tests/eastern_shapes_pil.png
pycoast/tests/grid_europe.png
pycoast/tests/grid_europe_agg.png
pycoast/tests/grid_europe_agg_txt.png
pycoast/tests/grid_from_dict_agg.png
pycoast/tests/grid_from_dict_pil.png
pycoast/tests/grid_geos.png
pycoast/tests/grid_geos_agg.png
pycoast/tests/grid_germ.png
pycoast/tests/grid_nh.png
pycoast/tests/grid_nh_agg.png
pycoast/tests/grid_nh_cfg_agg.png
pycoast/tests/lonlat_boundary_cross.png
pycoast/tests/nh_cities_agg.ini
pycoast/tests/nh_cities_agg.png
pycoast/tests/nh_cities_from_dict_agg.png
pycoast/tests/nh_cities_from_dict_pil.png
pycoast/tests/nh_cities_pil.ini
pycoast/tests/nh_cities_pil.png
pycoast/tests/nh_one_shapefile.ini
pycoast/tests/nh_points_agg.ini
pycoast/tests/nh_points_agg.png
pycoast/tests/nh_points_cfg_pil.png
pycoast/tests/nh_points_pil.ini
pycoast/tests/nh_points_pil.png
pycoast/tests/nh_polygons.png
pycoast/tests/nh_polygons_agg.png
pycoast/tests/no_h_scratch_agg.png
pycoast/tests/no_h_scratch_pil.png
pycoast/tests/no_v_scratch_agg.png
pycoast/tests/no_v_scratch_pil.png
pycoast/tests/one_shapefile_from_cfg_agg.png
pycoast/tests/one_shapefile_from_cfg_pil.png
pycoast/tests/test_pycoast.py
pycoast/tests/two_shapefiles_agg.png
pycoast/tests/two_shapefiles_pil.png
pycoast/tests/western_shapes_agg.png
pycoast/tests/western_shapes_pil.png
pycoast/tests/test_data/DejaVuSerif.ttf
pycoast/tests/test_data/test_config.ini
pycoast-1.7.1.dist-info/AUTHORS.md
pycoast-1.7.1.dist-info/LICENSE.txt
pycoast-1.7.1.dist-info/METADATA
pycoast-1.7.1.dist-info/WHEEL
pycoast-1.7.1.dist-info/top_level.txt
pycoast-1.7.1.dist-info/RECORD
