Metadata-Version: 2.1
Name: pycoast
Version: 1.7.1
Summary: Writing of coastlines, borders and rivers to images in Python
Author: Esben S. Nielsen
Author-email: esn@dmi.dk
Classifier: Development Status :: 5 - Production/Stable
Classifier: License :: OSI Approved :: GNU General Public License v3 (GPLv3)
Classifier: Programming Language :: Python
Classifier: Operating System :: OS Independent
Classifier: Intended Audience :: Science/Research
Classifier: Topic :: Scientific/Engineering
Requires-Python: >3.9
License-File: LICENSE.txt
License-File: AUTHORS.md
Requires-Dist: aggdraw
Requires-Dist: pyshp
Requires-Dist: numpy
Requires-Dist: pyproj
Requires-Dist: pillow
Provides-Extra: docs
Requires-Dist: sphinx ; extra == 'docs'
Requires-Dist: pyresample ; extra == 'docs'
Requires-Dist: pytest ; extra == 'docs'
Requires-Dist: pytest-lazy-fixtures ; extra == 'docs'
Requires-Dist: sphinx-rtd-theme ; extra == 'docs'
Requires-Dist: sphinxcontrib-apidoc ; extra == 'docs'
Provides-Extra: tests
Requires-Dist: pyresample ; extra == 'tests'
Requires-Dist: pytest ; extra == 'tests'
Requires-Dist: pytest-cov ; extra == 'tests'
Requires-Dist: coverage ; extra == 'tests'
Requires-Dist: coveralls ; extra == 'tests'
Requires-Dist: pytest-lazy-fixtures ; extra == 'tests'
